turta_lorahat/Turta_Accel.py
turta_lorahat/Turta_Analog.py
turta_lorahat/Turta_Digital.py
turta_lorahat/Turta_LoRa.py
turta_lorahat/__init__.py
turta_lorahat-1.0.0.dist-info/LICENCE
turta_lorahat-1.0.0.dist-info/METADATA
turta_lorahat-1.0.0.dist-info/WHEEL
turta_lorahat-1.0.0.dist-info/top_level.txt
turta_lorahat-1.0.0.dist-info/RECORD
