Metadata-Version: 2.1
Name: turta-lorahat
Version: 1.0.0
Summary: Python Libraries for Turta LoRa HAT
Home-page: https://www.turta.io/lorahat
Author: Turta LLC
Author-email: hello@turta.io
License: UNKNOWN
Project-URL: Documentation, https://docs.turta.io/raspberry-pi-hats/lora-hat
Project-URL: Community, https://community.turta.io
Project-URL: GitHub Repository, https://github.com/Turta-io/LoRaHAT
Platform: UNKNOWN
Classifier: Development Status :: 5 - Production/Stable
Classifier: Intended Audience :: Developers
Classifier: Programming Language :: Python
Classifier: License :: OSI Approved :: MIT License
Classifier: Operating System :: Unix
Classifier: Topic :: System :: Hardware
Requires-Dist: pyserial
Requires-Dist: RPi.GPIO
Requires-Dist: smbus
Requires-Dist: spidev
